rgc/__init__.py
rgc/utils/__init__.py
rgc/utils/data.py
rgc-0.9.0.dist-info/LICENSE
rgc-0.9.0.dist-info/METADATA
rgc-0.9.0.dist-info/WHEEL
rgc-0.9.0.dist-info/top_level.txt
rgc-0.9.0.dist-info/RECORD
