Metadata-Version: 2.1
Name: rgc
Version: 0.9.0
Summary: This is a template repository for Python projects that use uv for their dependency management.
Author-email: Mir Sazzat Hossain <mirsazzathossain@gmail.com>
Project-URL: Homepage, https://mirsazzathossain.github.io/radio-galaxy-classifier/
Project-URL: Repository, https://github.com/mirsazzathossain/radio-galaxy-classifier
Project-URL: Documentation, https://mirsazzathossain.github.io/radio-galaxy-classifier/
Keywords: python
Classifier: Programming Language :: Python :: 3
Classifier: License :: OSI Approved :: GNU Affero General Public License v3 or later (AGPLv3+)
Classifier: Operating System :: OS Independent
Requires-Python: <4.0,>=3.8
License-File: LICENSE
Requires-Dist: astropy >=5.2.2
Requires-Dist: astroquery >=0.4.7
Requires-Dist: bdsf >=1.11.1
Requires-Dist: numpy >=1.24.4
Requires-Dist: pandas >=2.0.3
Requires-Dist: pillow >=10.4.0
Requires-Dist: torch >=2.4.1
